aditya1/__init__.py
aditya1-0.1.dist-info/METADATA
aditya1-0.1.dist-info/WHEEL
aditya1-0.1.dist-info/top_level.txt
aditya1-0.1.dist-info/RECORD
