Metadata-Version: 2.1
Name: aditya1
Version: 0.1
Summary: add the number
Home-page: UNKNOWN
Author: adityasg
Author-email: adityatiwari@sganalytics.com
License: MIT
Platform: UNKNOWN
